{
  "name": "Lino-mixed en Acryls",
  "author": "Nic Heffels",
  "website": "nicheffels.nl",
  "text": "De wereld om me heen is mijn grote inspiratiebron. Creatief scheppen is voor mij een constante zoektocht. Voortdurend mijn eigen grenzen verleggen, vragen blijven stellen, het pas verworvene te evalueren  en zonodig los te laten. Het wekken van suggesties heeft meer waarde dan enkel noteren. “Less is more”. Sinds enkele jaren werk ik veel in lino-mixed techniek. Daar waar normaal gesproken het drukproces begint, sla ik een andere weg in. Er wordt geen afdruk gemaakt: de linoplaat is eindproduct. Elke lino-mixed is uniek en eenmalig.",
  "image0": "0.jpg",
  "image1": "1.jpg",
  "image2": "2.jpg"
}