{
  "name": "Houtenbeeldenatelier",
  "author": "Will Schropp",
  "website": "houtenbeelden.nl",
  "text": "Sinds 1985 laat ik zien, dat je als vormgever uitstekend gebruik kunt maken van hout dat afkomstig is van Nederlandse bomen. Ik gebruik de beeldtaal om mijn verhaal te vertellen. \"Het Leven\" en \"de droom te kunnen vliegen\" zijn steeds terugkerende thema's. Een beeld begint met een gedachte, dan maak ik schetsen totdat alle verhoudingen kloppen en vervolgens zoek ik hout dat er perfect bij past. Het beeld ontstaat door hakken en is daarom een sculptuur. Al jaren maak ik beelden van hout van soms meer dan 8000 jaar oud. En al ruim dertig jaar hangt er bij iedere tentoonstelling een jas van hout.",
  "image0": "0.jpg",
  "image1": "1.jpg",
  "image2": "2.jpg"
}